{
  "users": [
    {
      "id": "1",
      "email": "a@a.cl",
      "password": "1234***D"
    },
    {
      "id": "2",
      "email": "usuario2@example.com",
      "password": "password"
    },
    {
      "id": "3d91",
      "nombre": "Nolasco",
      "email": "n@n.cl",
      "password": "1234***D"
    },
    {
      "id": "9875",
      "nombre": "Scarleth",
      "email": "s@s.cl",
      "password": "1234***S"
    },
    {
      "id": "ff39",
      "nombre": "sfuente",
      "email": "sf@sf.cl",
      "password": "1234***S"
    }
  ],
  "products": [
    {
      "id": "1d2f",
      "trackingCode": "12",
      "image": "https://home.ripley.cl/store/Attachment/WOP/D327/2000390575605/2000390575605_2.jpg",
      "name": "Perfume 45",
      "description": "Rica fragancia",
      "price": 5000,
      "category": "perfumes"
    },
    {
      "id": "b52a",
      "trackingCode": "1234",
      "image": "https://belcorpchile.vtexassets.com/arquivos/ids/371894-800-800?v=638300586207500000&width=800&height=800&aspect=true",
      "name": "perfume men",
      "description": "perfume",
      "price": 12333,
      "category": "perfume"
    },
    {
      "id": "74de",
      "trackingCode": "34255",
      "image": "https://www.lg.com/content/dam/channel/wcms/cl/images/lavadoras/wd14vvc4s6c_aptpecl_escl_cl_c/Basic-450.jpg",
      "name": "Lavadora lg",
      "description": "lavadora",
      "price": 500000,
      "category": "linea blanca"
    },
    {
      "id": "7eb9",
      "trackingCode": "4536",
      "image": "https://apasionados-por-el-cafe.s3.amazonaws.com/wp-content/uploads/2023/08/cafe-mas-caro-mundo-apasionados-por-el-cafe.jpg",
      "name": "cafe",
      "description": "cafe rico",
      "price": 30000,
      "category": "te y cafe"
    },
    {
      "id": "4cb1",
      "trackingCode": "flor",
      "image": "https://belcorpchile.vtexassets.com/arquivos/ids/371894-800-800?v=638300586207500000&width=800&height=800&aspect=true",
      "name": "flore",
      "description": "floe",
      "price": 34322,
      "category": "flor"
    },
    {
      "id": "b907",
      "trackingCode": "24324",
      "image": "https://belcorpchile.vtexassets.com/arquivos/ids/371894-800-800?v=638300586207500000&width=800&height=800&aspect=true",
      "name": "caj23",
      "description": "cja",
      "price": 23,
      "category": "444"
    },
    {
      "id": "e6c4",
      "trackingCode": "65737",
      "image": "https://apasionados-por-el-cafe.s3.amazonaws.com/wp-content/uploads/2023/08/cafe-mas-caro-mundo-apasionados-por-el-cafe.jpg",
      "name": "cafe insta",
      "description": "cafe insta",
      "price": 356377,
      "category": "cafe"
    },
    {
      "id": "b4b1",
      "trackingCode": "12212",
      "image": "https://home.ripley.cl/store/Attachment/WOP/D327/2000390575605/2000390575605_2.jpg",
      "name": "perfume eros",
      "description": "perfume",
      "price": 121212,
      "category": "perfume"
    }
  ],
  "categories": [
    {
      "id": "1",
      "name": "Categoría 1"
    },
    {
      "id": "2",
      "name": "Categoría 2"
    }
  ],
  "bodegas": [
    {
      "id": "0fa5",
      "name": "Bodega 2",
      "location": "santiago",
      "capacity": 3
    },
    {
      "id": "f6c1",
      "name": "Bodega 34",
      "location": "lampa",
      "capacity": 100
    },
    {
      "id": "e6f1",
      "name": "Bodega 4",
      "location": "lampa",
      "capacity": 100
    },
    {
      "id": "476a",
      "name": "bodega 45",
      "location": "santiago",
      "capacity": 1000
    },
    {
      "id": "35a3",
      "name": "bodega 64",
      "location": "pichilemu",
      "capacity": 20000
    },
    {
      "id": "d6ad",
      "name": "vodega 78",
      "location": "conchali",
      "capacity": 232424
    },
    {
      "id": "fec1",
      "name": "odewga",
      "location": "ajajjs",
      "capacity": 17383
    }
  ],
  "movimientos": [
    {
      "id": "3229",
      "producto": "5a1c",
      "bodega": "f6c1",
      "cantidad": 30,
      "tipo": "entrada"
    },
    {
      "id": "2525",
      "producto": "1d2f",
      "bodega": "f6c1",
      "cantidad": 10,
      "tipo": "salida"
    },
    {
      "id": "8867",
      "producto": "74de",
      "bodega": "f6c1",
      "cantidad": 10,
      "tipo": "entrada"
    },
    {
      "id": "b3b3",
      "producto": "74de",
      "bodega": "d6ad",
      "cantidad": 130,
      "tipo": "entrada"
    },
    {
      "id": "b6a4",
      "producto": "74de",
      "bodega": "476a",
      "cantidad": 130,
      "tipo": "salida"
    }
  ]
}